Metadata-Version: 2.1
Name: profile-likelihood
Version: 0.6.1
Summary: Profile likelihood toolbox
Home-page: https://git.physics.byu.edu/yonatank/profile_likelihood
Author: Yonatan Kurniawan
Author-email: kurniawanyo@outlook.com
License: MIT
Platform: UNKNOWN
Classifier: Intended Audience :: Science/Research
Classifier: License :: OSI Approved :: MIT License
Classifier: Programming Language :: Python :: 3
Requires-Python: >=3.6
License-File: LICENSE
